divergent_beamsearch/__init__.py
divergent_beamsearch/algorithm.py
divergent_beamsearch-0.2.3.dist-info/METADATA
divergent_beamsearch-0.2.3.dist-info/WHEEL
divergent_beamsearch-0.2.3.dist-info/licenses/LICENCE
divergent_beamsearch-0.2.3.dist-info/RECORD
