Metadata-Version: 2.4
Name: divergent-beamsearch
Version: 0.2.3
Summary: A variant of the beam search algorithm that focuses on finding answers that maximize the probability of generating an answer before diverging into another subject.
License-File: LICENCE
Requires-Python: >=3.11
Requires-Dist: multi-choices-parser>=0.10.0
Requires-Dist: torch>=2.0.0
